optmap/__init__.py
optmap-0.0.1.dist-info/METADATA
optmap-0.0.1.dist-info/WHEEL
optmap-0.0.1.dist-info/RECORD
